configlog/__init__.py
configlog/setlogs.py
loguru_notification-0.0.7.dist-info/LICENSE
loguru_notification-0.0.7.dist-info/METADATA
loguru_notification-0.0.7.dist-info/WHEEL
loguru_notification-0.0.7.dist-info/top_level.txt
loguru_notification-0.0.7.dist-info/RECORD
