Metadata-Version: 2.1
Name: loguru-notification
Version: 0.0.7
Summary: Project logging printout
Home-page: https://github.com/supplayer/loguru-notification
Author: Supplayer
Author-email: x254724521@hotmail.com
License: UNKNOWN
Platform: UNKNOWN
Classifier: Programming Language :: Python :: 3
Classifier: License :: OSI Approved :: MIT License
Classifier: Operating System :: OS Independent
Requires-Python: >=3.6
Requires-Dist: loguru
Requires-Dist: CMRESHandler2
Requires-Dist: notifiers
